olfactory_navigation/__init__.py
olfactory_navigation/agent.py
olfactory_navigation/build_environment_gui.py
olfactory_navigation/environment.py
olfactory_navigation/simulation.py
olfactory_navigation/test_setups.py
olfactory_navigation/visualization.py
olfactory_navigation/agents/__init__.py
olfactory_navigation/agents/fsvi_agent.py
olfactory_navigation/agents/hsvi_agent.py
olfactory_navigation/agents/infotaxis_agent.py
olfactory_navigation/agents/pbvi_agent.py
olfactory_navigation/agents/pbvi_ger_agent.py
olfactory_navigation/agents/pbvi_ra_agent.py
olfactory_navigation/agents/pbvi_ssea_agent.py
olfactory_navigation/agents/pbvi_ssga_agent.py
olfactory_navigation/agents/pbvi_ssra_agent.py
olfactory_navigation/agents/perseus_agent.py
olfactory_navigation/agents/q_agent.py
olfactory_navigation/agents/qmdp_agent.py
olfactory_navigation/agents/model_based_util/__init__.py
olfactory_navigation/agents/model_based_util/belief.py
olfactory_navigation/agents/model_based_util/belief_value_mapping.py
olfactory_navigation/agents/model_based_util/environment_converter.py
olfactory_navigation/agents/model_based_util/mdp.py
olfactory_navigation/agents/model_based_util/pomdp.py
olfactory_navigation/agents/model_based_util/value_function.py
olfactory_navigation/agents/model_based_util/vi_solver.py
olfactory_navigation-1.0.9.dist-info/licenses/LICENSE
olfactory_navigation-1.0.9.dist-info/METADATA
olfactory_navigation-1.0.9.dist-info/WHEEL
olfactory_navigation-1.0.9.dist-info/top_level.txt
olfactory_navigation-1.0.9.dist-info/RECORD
