Metadata-Version: 2.4
Name: olfactory-navigation
Version: 1.0.9
Summary: A package to simulate the process of olfactory navigation in various environment using pre-built agents or user-made agents.
Author-email: Arnaud Ruymaekers <contact.aruymaekers@gmail.com>
License: MIT License
Project-URL: Homepage, https://pimlb.github.io/olfactory-navigation
Requires-Python: >=3.11
License-File: LICENSE
Dynamic: license-file
